{
  "__type__": "cc.Mesh",
  "_name": "",
  "_objFlags": 0,
  "_native": ".bin",
  "_struct": {
    "primitives": [
      {
        "primitiveMode": 7,
        "vertexBundelIndices": [
          0
        ],
        "geometricInfo": {
          "view": {
            "offset": 33920,
            "length": 5088,
            "count": 1272,
            "stride": 4
          }
        },
        "indexView": {
          "offset": 39008,
          "length": 2472,
          "count": 1236,
          "stride": 2
        }
      }
    ],
    "vertexBundles": [
      {
        "view": {
          "offset": 0,
          "length": 33920,
          "count": 424,
          "stride": 80
        },
        "attributes": [
          {
            "name": "a_position",
            "format": 32,
            "isNormalized": false
          },
          {
            "name": "a_normal",
            "format": 32,
            "isNormalized": false
          },
          {
            "name": "a_texCoord",
            "format": 21,
            "isNormalized": false
          },
          {
            "name": "a_tangent",
            "format": 43,
            "isNormalized": false
          },
          {
            "name": "a_joints",
            "format": 41,
            "isNormalized": false
          },
          {
            "name": "a_weights",
            "format": 43,
            "isNormalized": false
          },
          {
            "name": "a_texCoord1",
            "format": 21,
            "isNormalized": false
          }
        ]
      }
    ],
    "minPosition": {
      "__type__": "cc.Vec3",
      "x": -0.16822941390430543,
      "y": 1.2050768197514143,
      "z": -0.09754962496016614
    },
    "maxPosition": {
      "__type__": "cc.Vec3",
      "x": 0.1677375591696095,
      "y": 1.556070237420502,
      "z": 0.1520773905657649
    }
  },
  "_dataLength": 41480,
  "_hash": 2264869835
}